streamlit_islands/__init__.py
streamlit_islands/demo.py
streamlit_islands/test.py
streamlit_islands-0.0.8.dist-info/LICENSE.txt
streamlit_islands-0.0.8.dist-info/METADATA
streamlit_islands-0.0.8.dist-info/WHEEL
streamlit_islands-0.0.8.dist-info/top_level.txt
streamlit_islands-0.0.8.dist-info/RECORD
