Metadata-Version: 2.1
Name: streamlit-islands
Version: 0.0.8
Summary: Separate static content from dynamic content in Streamlit
Home-page: https://github.com/bouzidanas/streamlit-islands
Author: Anas Bouzid
Author-email: anasbouzid@gmail.com
License: UNKNOWN
Platform: UNKNOWN
Requires-Python: >=3.6
License-File: LICENSE.txt
Requires-Dist: streamlit (>=0.63)
